{
  "protocol_version" : "0.0.6",
  "configuration" : {
    "version" : "(6.13.0) (explicit/dd9688d8)",
    "tlc" : "__thread",
    "sigsgev" : "normal",
    "notifications" : "kqueue",
    "architecture" : "arm64",
    "disabled_features" : "com,shared_perfcounters",
    "smallconfig" : "disabled",
    "bigarrays" : "disabled",
    "softdebug" : "enabled",
    "interpreter" : "enabled",
    "llvm_support" : "disabled",
    "suspend" : "preemptive"
  },
  "memory" : {
    "Resident Size" : "726433792",
    "Virtual Size" : "421926322176",
    "minor_gc_time" : "0",
    "major_gc_time" : "60195",
    "minor_gc_count" : "0",
    "major_gc_count" : "3",
    "major_gc_time_concurrent" : "0"
 },
  "threads" : [
 {
    "is_managed" : false,
    "offset_free_hash" : "0x0",
    "offset_rich_hash" : "0x0",
    "crashed" : false,
    "native_thread_id" : "0x177bc3000",
    "thread_info_addr" : "0x2c102d200",
    "thread_name" : "tid_14d03",
    "ctx" : {
      "IP" : "0x188c16830",
      "SP" : "0x177bc2d20",
      "BP" : "0x177bc2d30"
  },
    "unmanaged_frames" : [
  {
      "is_managed" : "false",
      "native_address" : "0x280cffb40",
      "native_offset" : "0x00000"
   }
,
  {
      "is_managed" : "false",
      "native_address" : "0x280e35ecc",
      "native_offset" : "0x00000"
   }
,
  {
      "is_managed" : "false",
      "native_address" : "0x280e36244",
      "native_offset" : "0x00000"
   }
,
  {
      "is_managed" : "false",
      "native_address" : "0x280e35ff0",
      "native_offset" : "0x00000"
   }
,
  {
      "is_managed" : "false",
      "native_address" : "0x280d40a30",
      "native_offset" : "0x00000"
   }
,
  {
      "is_managed" : "false",
      "native_address" : "0x188c85a24",
      "native_offset" : "0x00000"
   }
,
  {
      "is_managed" : "false",
      "native_address" : "0x188aa9eac",
      "native_offset" : "0x00000"
   }
,
  {
      "is_managed" : "false",
      "native_address" : "0x188aaa55c",
      "native_offset" : "0x00000"
   }
,
  {
      "is_managed" : "false",
      "native_address" : "0x103a2a2bc",
      "native_offset" : "0x00000"
   }
,
  {
      "is_managed" : "false",
      "native_address" : "0x1016950d8",
      "native_offset" : "0x00000"
   }
,
  {
      "is_managed" : "false",
      "native_address" : "0x101695d68",
      "native_offset" : "0x00000"
   }
,
  {
      "is_managed" : "false",
      "native_address" : "0x1018e201c",
      "native_offset" : "0x00000"
   }
,
  {
      "is_managed" : "false",
      "native_address" : "0x188c57034",
      "native_offset" : "0x00000"
   }
,
  {
      "is_managed" : "false",
      "native_address" : "0x188c51e3c",
      "native_offset" : "0x00000"
   }

  ]
 },
 {
    "is_managed" : false,
    "offset_free_hash" : "0x0",
    "offset_rich_hash" : "0x0",
    "crashed" : false,
    "native_thread_id" : "0x28aa07000",
    "thread_info_addr" : "0x14845dc00",
    "thread_name" : "Thread Pool I/O Selector",
    "ctx" : {
      "IP" : "0x188c21a14",
      "SP" : "0x28aa06af0",
      "BP" : "0x28aa06cf0"
  },
    "unmanaged_frames" : [
  {
      "is_managed" : "false",
      "native_address" : "0x280cffb40",
      "native_offset" : "0x00000"
   }
,
  {
      "is_managed" : "false",
      "native_address" : "0x280e35ecc",
      "native_offset" : "0x00000"
   }
,
  {
      "is_managed" : "false",
      "native_address" : "0x280e36244",
      "native_offset" : "0x00000"
   }
,
  {
      "is_managed" : "false",
      "native_address" : "0x280e35ff0",
      "native_offset" : "0x00000"
   }
,
  {
      "is_managed" : "false",
      "native_address" : "0x280d40a30",
      "native_offset" : "0x00000"
   }
,
  {
      "is_managed" : "false",
      "native_address" : "0x188c85a24",
      "native_offset" : "0x00000"
   }
,
  {
      "is_managed" : "false",
      "native_address" : "0x280e87f40",
      "native_offset" : "0x00000"
   }
,
  {
      "is_managed" : "false",
      "native_address" : "0x280e3b4d8",
      "native_offset" : "0x00000"
   }
,
  {
      "is_managed" : "false",
      "native_address" : "0x280e3ae54",
      "native_offset" : "0x00000"
   }
,
  {
      "is_managed" : "false",
      "native_address" : "0x280e36cb4",
      "native_offset" : "0x00000"
   }
,
  {
      "is_managed" : "false",
      "native_address" : "0x280e36b60",
      "native_offset" : "0x00000"
   }
,
  {
      "is_managed" : "false",
      "native_address" : "0x280eb60d0",
      "native_offset" : "0x00000"
   }
,
  {
      "is_managed" : "false",
      "native_address" : "0x280eb6058",
      "native_offset" : "0x00000"
   }
,
  {
      "is_managed" : "false",
      "native_address" : "0x188c57034",
      "native_offset" : "0x00000"
   }
,
  {
      "is_managed" : "false",
      "native_address" : "0x188c51e3c",
      "native_offset" : "0x00000"
   }

  ]
 },
 {
    "is_managed" : false,
    "offset_free_hash" : "0x0",
    "offset_rich_hash" : "0x0",
    "crashed" : false,
    "native_thread_id" : "0x177aab000",
    "thread_info_addr" : "0x2857dac00",
    "thread_name" : "tid_14f03",
    "ctx" : {
      "IP" : "0x188c16830",
      "SP" : "0x177aaad20",
      "BP" : "0x177aaad30"
  },
    "unmanaged_frames" : [
  {
      "is_managed" : "false",
      "native_address" : "0x280cffb40",
      "native_offset" : "0x00000"
   }
,
  {
      "is_managed" : "false",
      "native_address" : "0x280e35ecc",
      "native_offset" : "0x00000"
   }
,
  {
      "is_managed" : "false",
      "native_address" : "0x280e36244",
      "native_offset" : "0x00000"
   }
,
  {
      "is_managed" : "false",
      "native_address" : "0x280e35ff0",
      "native_offset" : "0x00000"
   }
,
  {
      "is_managed" : "false",
      "native_address" : "0x280d40a30",
      "native_offset" : "0x00000"
   }
,
  {
      "is_managed" : "false",
      "native_address" : "0x188c85a24",
      "native_offset" : "0x00000"
   }
,
  {
      "is_managed" : "false",
      "native_address" : "0x188aa9eac",
      "native_offset" : "0x00000"
   }
,
  {
      "is_managed" : "false",
      "native_address" : "0x188aaa55c",
      "native_offset" : "0x00000"
   }
,
  {
      "is_managed" : "false",
      "native_address" : "0x103a2a2bc",
      "native_offset" : "0x00000"
   }
,
  {
      "is_managed" : "false",
      "native_address" : "0x1016950d8",
      "native_offset" : "0x00000"
   }
,
  {
      "is_managed" : "false",
      "native_address" : "0x101695d68",
      "native_offset" : "0x00000"
   }
,
  {
      "is_managed" : "false",
      "native_address" : "0x1018e201c",
      "native_offset" : "0x00000"
   }
,
  {
      "is_managed" : "false",
      "native_address" : "0x188c57034",
      "native_offset" : "0x00000"
   }
,
  {
      "is_managed" : "false",
      "native_address" : "0x188c51e3c",
      "native_offset" : "0x00000"
   }

  ]
 },
 {
    "is_managed" : false,
    "offset_free_hash" : "0x0",
    "offset_rich_hash" : "0x0",
    "crashed" : false,
    "native_thread_id" : "0x177c4f000",
    "thread_info_addr" : "0x2857cfc00",
    "thread_name" : "tid_11303",
    "ctx" : {
      "IP" : "0x188c16830",
      "SP" : "0x177c4ed20",
      "BP" : "0x177c4ed30"
  },
    "unmanaged_frames" : [
  {
      "is_managed" : "false",
      "native_address" : "0x280cffb40",
      "native_offset" : "0x00000"
   }
,
  {
      "is_managed" : "false",
      "native_address" : "0x280e35ecc",
      "native_offset" : "0x00000"
   }
,
  {
      "is_managed" : "false",
      "native_address" : "0x280e36244",
      "native_offset" : "0x00000"
   }
,
  {
      "is_managed" : "false",
      "native_address" : "0x280e35ff0",
      "native_offset" : "0x00000"
   }
,
  {
      "is_managed" : "false",
      "native_address" : "0x280d40a30",
      "native_offset" : "0x00000"
   }
,
  {
      "is_managed" : "false",
      "native_address" : "0x188c85a24",
      "native_offset" : "0x00000"
   }
,
  {
      "is_managed" : "false",
      "native_address" : "0x188aa9eac",
      "native_offset" : "0x00000"
   }
,
  {
      "is_managed" : "false",
      "native_address" : "0x188aaa55c",
      "native_offset" : "0x00000"
   }
,
  {
      "is_managed" : "false",
      "native_address" : "0x103a2a2bc",
      "native_offset" : "0x00000"
   }
,
  {
      "is_managed" : "false",
      "native_address" : "0x1016950d8",
      "native_offset" : "0x00000"
   }
,
  {
      "is_managed" : "false",
      "native_address" : "0x101695d68",
      "native_offset" : "0x00000"
   }
,
  {
      "is_managed" : "false",
      "native_address" : "0x1018e201c",
      "native_offset" : "0x00000"
   }
,
  {
      "is_managed" : "false",
      "native_address" : "0x188c57034",
      "native_offset" : "0x00000"
   }
,
  {
      "is_managed" : "false",
      "native_address" : "0x188c51e3c",
      "native_offset" : "0x00000"
   }

  ]
 },
 {
    "is_managed" : true,
    "offset_free_hash" : "0xd07c82684",
    "offset_rich_hash" : "0xd07c8284b",
    "crashed" : false,
    "native_thread_id" : "0x2c066b000",
    "thread_info_addr" : "0x14805ac00",
    "thread_name" : "Background Worker",
    "ctx" : {
      "IP" : "0x188c1a0ac",
      "SP" : "0x2c066a5b0",
      "BP" : "0x2c066a640"
  },
    "managed_frames" : [
  {
      "is_managed" : "false",
      "native_address" : "unregistered"
   }
,
  {
      "is_managed" : "true",
      "guid" : "8F30377C-D614-4C70-A387-57E003943D53",
      "token" : "0x00000",
      "native_offset" : "0x0",
      "filename" : "mscorlib.dll",
      "sizeofimage" : "0x470000",
      "timestamp" : "0xc8150380",
      "il_offset" : "0xffffffff"
   }
,
  {
      "is_managed" : "true",
      "guid" : "8F30377C-D614-4C70-A387-57E003943D53",
      "token" : "0x6001fa4",
      "native_offset" : "0x0",
      "filename" : "mscorlib.dll",
      "sizeofimage" : "0x470000",
      "timestamp" : "0xc8150380",
      "il_offset" : "0x00019"
   }
,
  {
      "is_managed" : "true",
      "guid" : "745A2837-378F-45E1-A885-07E8AC9E2DEE",
      "token" : "0x6000c44",
      "native_offset" : "0x0",
      "filename" : "Unity.VisualScripting.Core.Editor.dll",
      "sizeofimage" : "0x130000",
      "timestamp" : "0xb2545eab",
      "il_offset" : "0x00092"
   }
,
  {
      "is_managed" : "true",
      "guid" : "8F30377C-D614-4C70-A387-57E003943D53",
      "token" : "0x6001f7d",
      "native_offset" : "0x0",
      "filename" : "mscorlib.dll",
      "sizeofimage" : "0x470000",
      "timestamp" : "0xc8150380",
      "il_offset" : "0x00014"
   }
,
  {
      "is_managed" : "true",
      "guid" : "8F30377C-D614-4C70-A387-57E003943D53",
      "token" : "0x6001f25",
      "native_offset" : "0x0",
      "filename" : "mscorlib.dll",
      "sizeofimage" : "0x470000",
      "timestamp" : "0xc8150380",
      "il_offset" : "0x00071"
   }
,
  {
      "is_managed" : "true",
      "guid" : "8F30377C-D614-4C70-A387-57E003943D53",
      "token" : "0x6001f23",
      "native_offset" : "0x0",
      "filename" : "mscorlib.dll",
      "sizeofimage" : "0x470000",
      "timestamp" : "0xc8150380",
      "il_offset" : "0x00000"
   }
,
  {
      "is_managed" : "true",
      "guid" : "8F30377C-D614-4C70-A387-57E003943D53",
      "token" : "0x6001f22",
      "native_offset" : "0x0",
      "filename" : "mscorlib.dll",
      "sizeofimage" : "0x470000",
      "timestamp" : "0xc8150380",
      "il_offset" : "0x0002b"
   }
,
  {
      "is_managed" : "true",
      "guid" : "8F30377C-D614-4C70-A387-57E003943D53",
      "token" : "0x6001f7f",
      "native_offset" : "0x0",
      "filename" : "mscorlib.dll",
      "sizeofimage" : "0x470000",
      "timestamp" : "0xc8150380",
      "il_offset" : "0x00008"
   }
,
  {
      "is_managed" : "true",
      "guid" : "8F30377C-D614-4C70-A387-57E003943D53",
      "token" : "0x00000",
      "native_offset" : "0x0",
      "filename" : "mscorlib.dll",
      "sizeofimage" : "0x470000",
      "timestamp" : "0xc8150380",
      "il_offset" : "0x00065"
   }

  ],
  "unmanaged_frames" : [
 {
    "is_managed" : "false",
    "native_address" : "0x280cffb40",
    "native_offset" : "0x00000"
  }
,
 {
    "is_managed" : "false",
    "native_address" : "0x280e35ecc",
    "native_offset" : "0x00000"
  }
,
 {
    "is_managed" : "false",
    "native_address" : "0x280e36244",
    "native_offset" : "0x00000"
  }
,
 {
    "is_managed" : "false",
    "native_address" : "0x280e35ff0",
    "native_offset" : "0x00000"
  }
,
 {
    "is_managed" : "false",
    "native_address" : "0x280d40a30",
    "native_offset" : "0x00000"
  }
,
 {
    "is_managed" : "false",
    "native_address" : "0x188c85a24",
    "native_offset" : "0x00000"
  }
,
 {
    "is_managed" : "false",
    "native_address" : "0x188c57628",
    "native_offset" : "0x00000"
  }
,
 {
    "is_managed" : "false",
    "native_address" : "0x280e854cc",
    "native_offset" : "0x00000"
  }
,
 {
    "is_managed" : "false",
    "native_address" : "0x280e8f0ac",
    "native_offset" : "0x00000"
  }
,
 {
    "is_managed" : "false",
    "native_address" : "0x280e2fb14",
    "native_offset" : "0x00000"
  }
,
 {
    "is_managed" : "false",
    "native_address" : "0x280ddae6c",
    "native_offset" : "0x00000"
  }
,
 {
    "is_managed" : "true",
    "guid" : "8F30377C-D614-4C70-A387-57E003943D53",
    "token" : "0x00000",
    "native_offset" : "0x0",
    "filename" : "mscorlib.dll",
    "sizeofimage" : "0x470000",
    "timestamp" : "0xc8150380",
    "il_offset" : "0x00000"
  }
,
 {
    "is_managed" : "true",
    "guid" : "8F30377C-D614-4C70-A387-57E003943D53",
    "token" : "0x6001fa4",
    "native_offset" : "0x0",
    "filename" : "mscorlib.dll",
    "sizeofimage" : "0x470000",
    "timestamp" : "0xc8150380",
    "il_offset" : "0x00000"
  }
,
 {
    "is_managed" : "true",
    "guid" : "745A2837-378F-45E1-A885-07E8AC9E2DEE",
    "token" : "0x6000c44",
    "native_offset" : "0x0",
    "filename" : "Unity.VisualScripting.Core.Editor.dll",
    "sizeofimage" : "0x130000",
    "timestamp" : "0xb2545eab",
    "il_offset" : "0x00000"
  }
,
 {
    "is_managed" : "true",
    "guid" : "8F30377C-D614-4C70-A387-57E003943D53",
    "token" : "0x6001f7d",
    "native_offset" : "0x0",
    "filename" : "mscorlib.dll",
    "sizeofimage" : "0x470000",
    "timestamp" : "0xc8150380",
    "il_offset" : "0x00000"
  }
,
 {
    "is_managed" : "true",
    "guid" : "8F30377C-D614-4C70-A387-57E003943D53",
    "token" : "0x6001f25",
    "native_offset" : "0x0",
    "filename" : "mscorlib.dll",
    "sizeofimage" : "0x470000",
    "timestamp" : "0xc8150380",
    "il_offset" : "0x00000"
  }
,
 {
    "is_managed" : "true",
    "guid" : "8F30377C-D614-4C70-A387-57E003943D53",
    "token" : "0x6001f23",
    "native_offset" : "0x0",
    "filename" : "mscorlib.dll",
    "sizeofimage" : "0x470000",
    "timestamp" : "0xc8150380",
    "il_offset" : "0x00000"
  }
,
 {
    "is_managed" : "true",
    "guid" : "8F30377C-D614-4C70-A387-57E003943D53",
    "token" : "0x6001f22",
    "native_offset" : "0x0",
    "filename" : "mscorlib.dll",
    "sizeofimage" : "0x470000",
    "timestamp" : "0xc8150380",
    "il_offset" : "0x00000"
  }
,
 {
    "is_managed" : "true",
    "guid" : "8F30377C-D614-4C70-A387-57E003943D53",
    "token" : "0x6001f7f",
    "native_offset" : "0x0",
    "filename" : "mscorlib.dll",
    "sizeofimage" : "0x470000",
    "timestamp" : "0xc8150380",
    "il_offset" : "0x00000"
  }
,
 {
    "is_managed" : "true",
    "guid" : "8F30377C-D614-4C70-A387-57E003943D53",
    "token" : "0x00000",
    "native_offset" : "0x0",
    "filename" : "mscorlib.dll",
    "sizeofimage" : "0x470000",
    "timestamp" : "0xc8150380",
    "il_offset" : "0x00000"
  }
,
 {
    "is_managed" : "false",
    "native_address" : "0x280c8f964",
    "native_offset" : "0x00000"
  }
,
 {
    "is_managed" : "false",
    "native_address" : "0x280e14ecc",
    "native_offset" : "0x00000"
  }
,
 {
    "is_managed" : "false",
    "native_address" : "0x280e16878",
    "native_offset" : "0x00000"
  }
,
 {
    "is_managed" : "false",
    "native_address" : "0x280e36da8",
    "native_offset" : "0x00000"
  }
,
 {
    "is_managed" : "false",
    "native_address" : "0x280e36b60",
    "native_offset" : "0x00000"
  }
,
 {
    "is_managed" : "false",
    "native_address" : "0x280eb60d0",
    "native_offset" : "0x00000"
  }
,
 {
    "is_managed" : "false",
    "native_address" : "0x280eb6058",
    "native_offset" : "0x00000"
  }
,
 {
    "is_managed" : "false",
    "native_address" : "0x188c57034",
    "native_offset" : "0x00000"
  }
,
 {
    "is_managed" : "false",
    "native_address" : "0x188c51e3c",
    "native_offset" : "0x00000"
  }

 ]
},
{
  "is_managed" : false,
  "offset_free_hash" : "0x0",
  "offset_rich_hash" : "0x0",
  "crashed" : false,
  "native_thread_id" : "0x2c202f000",
  "thread_info_addr" : "0x116850a00",
  "thread_name" : "tid_783f",
  "ctx" : {
    "IP" : "0x188c16848",
    "SP" : "0x2c202edc0",
    "BP" : "0x2c202ee50"
 },
  "unmanaged_frames" : [
 {
    "is_managed" : "false",
    "native_address" : "0x280cffb40",
    "native_offset" : "0x00000"
  }
,
 {
    "is_managed" : "false",
    "native_address" : "0x280e35ecc",
    "native_offset" : "0x00000"
  }
,
 {
    "is_managed" : "false",
    "native_address" : "0x280e36244",
    "native_offset" : "0x00000"
  }
,
 {
    "is_managed" : "false",
    "native_address" : "0x280e35ff0",
    "native_offset" : "0x00000"
  }
,
 {
    "is_managed" : "false",
    "native_address" : "0x280d40a30",
    "native_offset" : "0x00000"
  }
,
 {
    "is_managed" : "false",
    "native_address" : "0x188c85a24",
    "native_offset" : "0x00000"
  }
,
 {
    "is_managed" : "false",
    "native_address" : "0x280d8e71c",
    "native_offset" : "0x00000"
  }
,
 {
    "is_managed" : "false",
    "native_address" : "0x280e36cb4",
    "native_offset" : "0x00000"
  }
,
 {
    "is_managed" : "false",
    "native_address" : "0x280e36b60",
    "native_offset" : "0x00000"
  }
,
 {
    "is_managed" : "false",
    "native_address" : "0x280eb60d0",
    "native_offset" : "0x00000"
  }
,
 {
    "is_managed" : "false",
    "native_address" : "0x280eb6058",
    "native_offset" : "0x00000"
  }
,
 {
    "is_managed" : "false",
    "native_address" : "0x188c57034",
    "native_offset" : "0x00000"
  }
,
 {
    "is_managed" : "false",
    "native_address" : "0x188c51e3c",
    "native_offset" : "0x00000"
  }

 ]
},
{
  "is_managed" : false,
  "offset_free_hash" : "0x0",
  "offset_rich_hash" : "0x0",
  "crashed" : false,
  "native_thread_id" : "0x177993000",
  "thread_info_addr" : "0x285241800",
  "thread_name" : "tid_db0b",
  "ctx" : {
    "IP" : "0x188c16830",
    "SP" : "0x177992d20",
    "BP" : "0x177992d30"
 },
  "unmanaged_frames" : [
 {
    "is_managed" : "false",
    "native_address" : "0x280cffb40",
    "native_offset" : "0x00000"
  }
,
 {
    "is_managed" : "false",
    "native_address" : "0x280e35ecc",
    "native_offset" : "0x00000"
  }
,
 {
    "is_managed" : "false",
    "native_address" : "0x280e36244",
    "native_offset" : "0x00000"
  }
,
 {
    "is_managed" : "false",
    "native_address" : "0x280e35ff0",
    "native_offset" : "0x00000"
  }
,
 {
    "is_managed" : "false",
    "native_address" : "0x280d40a30",
    "native_offset" : "0x00000"
  }
,
 {
    "is_managed" : "false",
    "native_address" : "0x188c85a24",
    "native_offset" : "0x00000"
  }
,
 {
    "is_managed" : "false",
    "native_address" : "0x188aa9eac",
    "native_offset" : "0x00000"
  }
,
 {
    "is_managed" : "false",
    "native_address" : "0x188aaa55c",
    "native_offset" : "0x00000"
  }
,
 {
    "is_managed" : "false",
    "native_address" : "0x103a2a2bc",
    "native_offset" : "0x00000"
  }
,
 {
    "is_managed" : "false",
    "native_address" : "0x1016950d8",
    "native_offset" : "0x00000"
  }
,
 {
    "is_managed" : "false",
    "native_address" : "0x101695d68",
    "native_offset" : "0x00000"
  }
,
 {
    "is_managed" : "false",
    "native_address" : "0x1018e201c",
    "native_offset" : "0x00000"
  }
,
 {
    "is_managed" : "false",
    "native_address" : "0x188c57034",
    "native_offset" : "0x00000"
  }
,
 {
    "is_managed" : "false",
    "native_address" : "0x188c51e3c",
    "native_offset" : "0x00000"
  }

 ]
},
{
  "is_managed" : true,
  "offset_free_hash" : "0xfb24c96f8",
  "offset_rich_hash" : "0xfb24c9881",
  "crashed" : false,
  "native_thread_id" : "0x2c0287000",
  "thread_info_addr" : "0x2856d9a00",
  "thread_name" : "tid_3fd13",
  "ctx" : {
    "IP" : "0x188c1a0ac",
    "SP" : "0x2c0286540",
    "BP" : "0x2c02865d0"
 },
  "managed_frames" : [
 {
    "is_managed" : "false",
    "native_address" : "unregistered"
  }
,
 {
    "is_managed" : "true",
    "guid" : "8F30377C-D614-4C70-A387-57E003943D53",
    "token" : "0x00000",
    "native_offset" : "0x0",
    "filename" : "mscorlib.dll",
    "sizeofimage" : "0x470000",
    "timestamp" : "0xc8150380",
    "il_offset" : "0xffffffff"
  }
,
 {
    "is_managed" : "true",
    "guid" : "8F30377C-D614-4C70-A387-57E003943D53",
    "token" : "0x6001f5d",
    "native_offset" : "0x0",
    "filename" : "mscorlib.dll",
    "sizeofimage" : "0x470000",
    "timestamp" : "0xc8150380",
    "il_offset" : "0x0002f"
  }
,
 {
    "is_managed" : "true",
    "guid" : "8F30377C-D614-4C70-A387-57E003943D53",
    "token" : "0x6001f50",
    "native_offset" : "0x0",
    "filename" : "mscorlib.dll",
    "sizeofimage" : "0x470000",
    "timestamp" : "0xc8150380",
    "il_offset" : "0x0000e"
  }
,
 {
    "is_managed" : "true",
    "guid" : "8F30377C-D614-4C70-A387-57E003943D53",
    "token" : "0x6001f52",
    "native_offset" : "0x0",
    "filename" : "mscorlib.dll",
    "sizeofimage" : "0x470000",
    "timestamp" : "0xc8150380",
    "il_offset" : "0x00000"
  }
,
 {
    "is_managed" : "true",
    "guid" : "1E514392-43A4-4463-9221-1EB63CD2B663",
    "token" : "0x6005b9a",
    "native_offset" : "0x0",
    "filename" : "unityplastic.dll",
    "sizeofimage" : "0x4fe000",
    "timestamp" : "0x633f508a",
    "il_offset" : "0x00030"
  }
,
 {
    "is_managed" : "true",
    "guid" : "8F30377C-D614-4C70-A387-57E003943D53",
    "token" : "0x6001f7d",
    "native_offset" : "0x0",
    "filename" : "mscorlib.dll",
    "sizeofimage" : "0x470000",
    "timestamp" : "0xc8150380",
    "il_offset" : "0x00014"
  }
,
 {
    "is_managed" : "true",
    "guid" : "8F30377C-D614-4C70-A387-57E003943D53",
    "token" : "0x6001f25",
    "native_offset" : "0x0",
    "filename" : "mscorlib.dll",
    "sizeofimage" : "0x470000",
    "timestamp" : "0xc8150380",
    "il_offset" : "0x00071"
  }
,
 {
    "is_managed" : "true",
    "guid" : "8F30377C-D614-4C70-A387-57E003943D53",
    "token" : "0x6001f23",
    "native_offset" : "0x0",
    "filename" : "mscorlib.dll",
    "sizeofimage" : "0x470000",
    "timestamp" : "0xc8150380",
    "il_offset" : "0x00000"
  }
,
 {
    "is_managed" : "true",
    "guid" : "8F30377C-D614-4C70-A387-57E003943D53",
    "token" : "0x6001f22",
    "native_offset" : "0x0",
    "filename" : "mscorlib.dll",
    "sizeofimage" : "0x470000",
    "timestamp" : "0xc8150380",
    "il_offset" : "0x0002b"
  }
,
 {
    "is_managed" : "true",
    "guid" : "8F30377C-D614-4C70-A387-57E003943D53",
    "token" : "0x6001f7f",
    "native_offset" : "0x0",
    "filename" : "mscorlib.dll",
    "sizeofimage" : "0x470000",
    "timestamp" : "0xc8150380",
    "il_offset" : "0x00008"
  }
,
 {
    "is_managed" : "true",
    "guid" : "8F30377C-D614-4C70-A387-57E003943D53",
    "token" : "0x00000",
    "native_offset" : "0x0",
    "filename" : "mscorlib.dll",
    "sizeofimage" : "0x470000",
    "timestamp" : "0xc8150380",
    "il_offset" : "0x00065"
  }

 ],
"unmanaged_frames" : [
{
  "is_managed" : "false",
  "native_address" : "0x280cffb40",
  "native_offset" : "0x00000"
 }
,
{
  "is_managed" : "false",
  "native_address" : "0x280e35ecc",
  "native_offset" : "0x00000"
 }
,
{
  "is_managed" : "false",
  "native_address" : "0x280e36244",
  "native_offset" : "0x00000"
 }
,
{
  "is_managed" : "false",
  "native_address" : "0x280e35ff0",
  "native_offset" : "0x00000"
 }
,
{
  "is_managed" : "false",
  "native_address" : "0x280d40a30",
  "native_offset" : "0x00000"
 }
,
{
  "is_managed" : "false",
  "native_address" : "0x188c85a24",
  "native_offset" : "0x00000"
 }
,
{
  "is_managed" : "false",
  "native_address" : "0x188c57628",
  "native_offset" : "0x00000"
 }
,
{
  "is_managed" : "false",
  "native_address" : "0x280e854cc",
  "native_offset" : "0x00000"
 }
,
{
  "is_managed" : "false",
  "native_address" : "0x280e41c00",
  "native_offset" : "0x00000"
 }
,
{
  "is_managed" : "false",
  "native_address" : "0x280e41a34",
  "native_offset" : "0x00000"
 }
,
{
  "is_managed" : "false",
  "native_address" : "0x280e70f08",
  "native_offset" : "0x00000"
 }
,
{
  "is_managed" : "false",
  "native_address" : "0x280dda050",
  "native_offset" : "0x00000"
 }
,
{
  "is_managed" : "true",
  "guid" : "8F30377C-D614-4C70-A387-57E003943D53",
  "token" : "0x00000",
  "native_offset" : "0x0",
  "filename" : "mscorlib.dll",
  "sizeofimage" : "0x470000",
  "timestamp" : "0xc8150380",
  "il_offset" : "0x00000"
 }
,
{
  "is_managed" : "true",
  "guid" : "8F30377C-D614-4C70-A387-57E003943D53",
  "token" : "0x6001f5d",
  "native_offset" : "0x0",
  "filename" : "mscorlib.dll",
  "sizeofimage" : "0x470000",
  "timestamp" : "0xc8150380",
  "il_offset" : "0x00000"
 }
,
{
  "is_managed" : "true",
  "guid" : "8F30377C-D614-4C70-A387-57E003943D53",
  "token" : "0x6001f50",
  "native_offset" : "0x0",
  "filename" : "mscorlib.dll",
  "sizeofimage" : "0x470000",
  "timestamp" : "0xc8150380",
  "il_offset" : "0x00000"
 }
,
{
  "is_managed" : "true",
  "guid" : "8F30377C-D614-4C70-A387-57E003943D53",
  "token" : "0x6001f52",
  "native_offset" : "0x0",
  "filename" : "mscorlib.dll",
  "sizeofimage" : "0x470000",
  "timestamp" : "0xc8150380",
  "il_offset" : "0x00000"
 }
,
{
  "is_managed" : "true",
  "guid" : "1E514392-43A4-4463-9221-1EB63CD2B663",
  "token" : "0x6005b9a",
  "native_offset" : "0x0",
  "filename" : "unityplastic.dll",
  "sizeofimage" : "0x4fe000",
  "timestamp" : "0x633f508a",
  "il_offset" : "0x00000"
 }
,
{
  "is_managed" : "true",
  "guid" : "8F30377C-D614-4C70-A387-57E003943D53",
  "token" : "0x6001f7d",
  "native_offset" : "0x0",
  "filename" : "mscorlib.dll",
  "sizeofimage" : "0x470000",
  "timestamp" : "0xc8150380",
  "il_offset" : "0x00000"
 }
,
{
  "is_managed" : "true",
  "guid" : "8F30377C-D614-4C70-A387-57E003943D53",
  "token" : "0x6001f25",
  "native_offset" : "0x0",
  "filename" : "mscorlib.dll",
  "sizeofimage" : "0x470000",
  "timestamp" : "0xc8150380",
  "il_offset" : "0x00000"
 }
,
{
  "is_managed" : "true",
  "guid" : "8F30377C-D614-4C70-A387-57E003943D53",
  "token" : "0x6001f23",
  "native_offset" : "0x0",
  "filename" : "mscorlib.dll",
  "sizeofimage" : "0x470000",
  "timestamp" : "0xc8150380",
  "il_offset" : "0x00000"
 }
,
{
  "is_managed" : "true",
  "guid" : "8F30377C-D614-4C70-A387-57E003943D53",
  "token" : "0x6001f22",
  "native_offset" : "0x0",
  "filename" : "mscorlib.dll",
  "sizeofimage" : "0x470000",
  "timestamp" : "0xc8150380",
  "il_offset" : "0x00000"
 }
,
{
  "is_managed" : "true",
  "guid" : "8F30377C-D614-4C70-A387-57E003943D53",
  "token" : "0x6001f7f",
  "native_offset" : "0x0",
  "filename" : "mscorlib.dll",
  "sizeofimage" : "0x470000",
  "timestamp" : "0xc8150380",
  "il_offset" : "0x00000"
 }
,
{
  "is_managed" : "true",
  "guid" : "8F30377C-D614-4C70-A387-57E003943D53",
  "token" : "0x00000",
  "native_offset" : "0x0",
  "filename" : "mscorlib.dll",
  "sizeofimage" : "0x470000",
  "timestamp" : "0xc8150380",
  "il_offset" : "0x00000"
 }
,
{
  "is_managed" : "false",
  "native_address" : "0x280c8f964",
  "native_offset" : "0x00000"
 }
,
{
  "is_managed" : "false",
  "native_address" : "0x280e14ecc",
  "native_offset" : "0x00000"
 }
,
{
  "is_managed" : "false",
  "native_address" : "0x280e16878",
  "native_offset" : "0x00000"
 }
,
{
  "is_managed" : "false",
  "native_address" : "0x280e36da8",
  "native_offset" : "0x00000"
 }
,
{
  "is_managed" : "false",
  "native_address" : "0x280e36b60",
  "native_offset" : "0x00000"
 }
,
{
  "is_managed" : "false",
  "native_address" : "0x280eb60d0",
  "native_offset" : "0x00000"
 }
,
{
  "is_managed" : "false",
  "native_address" : "0x280eb6058",
  "native_offset" : "0x00000"
 }
,
{
  "is_managed" : "false",
  "native_address" : "0x188c57034",
  "native_offset" : "0x00000"
 }
,
{
  "is_managed" : "false",
  "native_address" : "0x188c51e3c",
  "native_offset" : "0x00000"
 }

]
},
{
"is_managed" : false,
"offset_free_hash" : "0x0",
"offset_rich_hash" : "0x0",
"crashed" : false,
"native_thread_id" : "0x177b37000",
"thread_info_addr" : "0x2b4465000",
"thread_name" : "tid_14e03",
"ctx" : {
  "IP" : "0x188c16830",
  "SP" : "0x177b36d20",
  "BP" : "0x177b36d30"
},
"unmanaged_frames" : [
{
  "is_managed" : "false",
  "native_address" : "0x280cffb40",
  "native_offset" : "0x00000"
 }
,
{
  "is_managed" : "false",
  "native_address" : "0x280e35ecc",
  "native_offset" : "0x00000"
 }
,
{
  "is_managed" : "false",
  "native_address" : "0x280e36244",
  "native_offset" : "0x00000"
 }
,
{
  "is_managed" : "false",
  "native_address" : "0x280e35ff0",
  "native_offset" : "0x00000"
 }
,
{
  "is_managed" : "false",
  "native_address" : "0x280d40a30",
  "native_offset" : "0x00000"
 }
,
{
  "is_managed" : "false",
  "native_address" : "0x188c85a24",
  "native_offset" : "0x00000"
 }
,
{
  "is_managed" : "false",
  "native_address" : "0x188aa9eac",
  "native_offset" : "0x00000"
 }
,
{
  "is_managed" : "false",
  "native_address" : "0x188aaa55c",
  "native_offset" : "0x00000"
 }
,
{
  "is_managed" : "false",
  "native_address" : "0x103a2a2bc",
  "native_offset" : "0x00000"
 }
,
{
  "is_managed" : "false",
  "native_address" : "0x1016950d8",
  "native_offset" : "0x00000"
 }
,
{
  "is_managed" : "false",
  "native_address" : "0x101695d68",
  "native_offset" : "0x00000"
 }
,
{
  "is_managed" : "false",
  "native_address" : "0x1018e201c",
  "native_offset" : "0x00000"
 }
,
{
  "is_managed" : "false",
  "native_address" : "0x188c57034",
  "native_offset" : "0x00000"
 }
,
{
  "is_managed" : "false",
  "native_address" : "0x188c51e3c",
  "native_offset" : "0x00000"
 }

]
},
{
"is_managed" : false,
"offset_free_hash" : "0x0",
"offset_rich_hash" : "0x0",
"crashed" : false,
"native_thread_id" : "0x281527000",
"thread_info_addr" : "0x146907000",
"thread_name" : "Finalizer",
"ctx" : {
  "IP" : "0x188c16830",
  "SP" : "0x281526de0",
  "BP" : "0x281526e50"
},
"unmanaged_frames" : [
{
  "is_managed" : "false",
  "native_address" : "0x280cffb40",
  "native_offset" : "0x00000"
 }
,
{
  "is_managed" : "false",
  "native_address" : "0x280e35ecc",
  "native_offset" : "0x00000"
 }
,
{
  "is_managed" : "false",
  "native_address" : "0x280e36244",
  "native_offset" : "0x00000"
 }
,
{
  "is_managed" : "false",
  "native_address" : "0x280e35ff0",
  "native_offset" : "0x00000"
 }
,
{
  "is_managed" : "false",
  "native_address" : "0x280d40a30",
  "native_offset" : "0x00000"
 }
,
{
  "is_managed" : "false",
  "native_address" : "0x188c85a24",
  "native_offset" : "0x00000"
 }
,
{
  "is_managed" : "false",
  "native_address" : "0x280e6f9c8",
  "native_offset" : "0x00000"
 }
,
{
  "is_managed" : "false",
  "native_address" : "0x280e36cb4",
  "native_offset" : "0x00000"
 }
,
{
  "is_managed" : "false",
  "native_address" : "0x280e36b60",
  "native_offset" : "0x00000"
 }
,
{
  "is_managed" : "false",
  "native_address" : "0x280eb60d0",
  "native_offset" : "0x00000"
 }
,
{
  "is_managed" : "false",
  "native_address" : "0x280eb6058",
  "native_offset" : "0x00000"
 }
,
{
  "is_managed" : "false",
  "native_address" : "0x188c57034",
  "native_offset" : "0x00000"
 }
,
{
  "is_managed" : "false",
  "native_address" : "0x188c51e3c",
  "native_offset" : "0x00000"
 }

]
},
{
"is_managed" : false,
"offset_free_hash" : "0x0",
"offset_rich_hash" : "0x0",
"crashed" : false,
"native_thread_id" : "0x29ba07000",
"thread_info_addr" : "0x28a7f0e00",
"thread_name" : "tid_28003",
"ctx" : {
  "IP" : "0x188c16830",
  "SP" : "0x29ba06d90",
  "BP" : "0x29ba06da0"
},
"unmanaged_frames" : [
{
  "is_managed" : "false",
  "native_address" : "0x280cffb40",
  "native_offset" : "0x00000"
 }
,
{
  "is_managed" : "false",
  "native_address" : "0x280e35ecc",
  "native_offset" : "0x00000"
 }
,
{
  "is_managed" : "false",
  "native_address" : "0x280e36244",
  "native_offset" : "0x00000"
 }
,
{
  "is_managed" : "false",
  "native_address" : "0x280e35ff0",
  "native_offset" : "0x00000"
 }
,
{
  "is_managed" : "false",
  "native_address" : "0x280d40a30",
  "native_offset" : "0x00000"
 }
,
{
  "is_managed" : "false",
  "native_address" : "0x188c85a24",
  "native_offset" : "0x00000"
 }
,
{
  "is_managed" : "false",
  "native_address" : "0x188aa9eac",
  "native_offset" : "0x00000"
 }
,
{
  "is_managed" : "false",
  "native_address" : "0x188aaa55c",
  "native_offset" : "0x00000"
 }
,
{
  "is_managed" : "false",
  "native_address" : "0x103a2a2bc",
  "native_offset" : "0x00000"
 }
,
{
  "is_managed" : "false",
  "native_address" : "0x10134dc14",
  "native_offset" : "0x00000"
 }
,
{
  "is_managed" : "false",
  "native_address" : "0x10173c4e4",
  "native_offset" : "0x00000"
 }
,
{
  "is_managed" : "false",
  "native_address" : "0x10173c480",
  "native_offset" : "0x00000"
 }
,
{
  "is_managed" : "false",
  "native_address" : "0x1018e201c",
  "native_offset" : "0x00000"
 }
,
{
  "is_managed" : "false",
  "native_address" : "0x188c57034",
  "native_offset" : "0x00000"
 }
,
{
  "is_managed" : "false",
  "native_address" : "0x188c51e3c",
  "native_offset" : "0x00000"
 }

]
},
{
"is_managed" : false,
"offset_free_hash" : "0x0",
"offset_rich_hash" : "0x0",
"crashed" : false,
"native_thread_id" : "0x177cdb000",
"thread_info_addr" : "0x14806fa00",
"thread_name" : "tid_14c03",
"ctx" : {
  "IP" : "0x188c16830",
  "SP" : "0x177cdad20",
  "BP" : "0x177cdad30"
},
"unmanaged_frames" : [
{
  "is_managed" : "false",
  "native_address" : "0x280cffb40",
  "native_offset" : "0x00000"
 }
,
{
  "is_managed" : "false",
  "native_address" : "0x280e35ecc",
  "native_offset" : "0x00000"
 }
,
{
  "is_managed" : "false",
  "native_address" : "0x280e36244",
  "native_offset" : "0x00000"
 }
,
{
  "is_managed" : "false",
  "native_address" : "0x280e35ff0",
  "native_offset" : "0x00000"
 }
,
{
  "is_managed" : "false",
  "native_address" : "0x280d40a30",
  "native_offset" : "0x00000"
 }
,
{
  "is_managed" : "false",
  "native_address" : "0x188c85a24",
  "native_offset" : "0x00000"
 }
,
{
  "is_managed" : "false",
  "native_address" : "0x188aa9eac",
  "native_offset" : "0x00000"
 }
,
{
  "is_managed" : "false",
  "native_address" : "0x188aaa55c",
  "native_offset" : "0x00000"
 }
,
{
  "is_managed" : "false",
  "native_address" : "0x103a2a2bc",
  "native_offset" : "0x00000"
 }
,
{
  "is_managed" : "false",
  "native_address" : "0x1016950d8",
  "native_offset" : "0x00000"
 }
,
{
  "is_managed" : "false",
  "native_address" : "0x101695d68",
  "native_offset" : "0x00000"
 }
,
{
  "is_managed" : "false",
  "native_address" : "0x1018e201c",
  "native_offset" : "0x00000"
 }
,
{
  "is_managed" : "false",
  "native_address" : "0x188c57034",
  "native_offset" : "0x00000"
 }
,
{
  "is_managed" : "false",
  "native_address" : "0x188c51e3c",
  "native_offset" : "0x00000"
 }

]
},
{
"is_managed" : false,
"offset_free_hash" : "0x0",
"offset_rich_hash" : "0x0",
"crashed" : false,
"native_thread_id" : "0x29b007000",
"thread_info_addr" : "0x148423200",
"thread_name" : "tid_7f33",
"ctx" : {
  "IP" : "0x188c16830",
  "SP" : "0x29b006d20",
  "BP" : "0x29b006d30"
},
"unmanaged_frames" : [
{
  "is_managed" : "false",
  "native_address" : "0x280cffb40",
  "native_offset" : "0x00000"
 }
,
{
  "is_managed" : "false",
  "native_address" : "0x280e35ecc",
  "native_offset" : "0x00000"
 }
,
{
  "is_managed" : "false",
  "native_address" : "0x280e36244",
  "native_offset" : "0x00000"
 }
,
{
  "is_managed" : "false",
  "native_address" : "0x280e35ff0",
  "native_offset" : "0x00000"
 }
,
{
  "is_managed" : "false",
  "native_address" : "0x280d40a30",
  "native_offset" : "0x00000"
 }
,
{
  "is_managed" : "false",
  "native_address" : "0x188c85a24",
  "native_offset" : "0x00000"
 }
,
{
  "is_managed" : "false",
  "native_address" : "0x188aa9eac",
  "native_offset" : "0x00000"
 }
,
{
  "is_managed" : "false",
  "native_address" : "0x188aaa55c",
  "native_offset" : "0x00000"
 }
,
{
  "is_managed" : "false",
  "native_address" : "0x103a2a2bc",
  "native_offset" : "0x00000"
 }
,
{
  "is_managed" : "false",
  "native_address" : "0x1016950d8",
  "native_offset" : "0x00000"
 }
,
{
  "is_managed" : "false",
  "native_address" : "0x101695d68",
  "native_offset" : "0x00000"
 }
,
{
  "is_managed" : "false",
  "native_address" : "0x1018e201c",
  "native_offset" : "0x00000"
 }
,
{
  "is_managed" : "false",
  "native_address" : "0x188c57034",
  "native_offset" : "0x00000"
 }
,
{
  "is_managed" : "false",
  "native_address" : "0x188c51e3c",
  "native_offset" : "0x00000"
 }

]
},
{
"is_managed" : false,
"offset_free_hash" : "0x0",
"offset_rich_hash" : "0x0",
"crashed" : false,
"native_thread_id" : "0x2b9a07000",
"thread_info_addr" : "0x1170ac400",
"thread_name" : "tid_cf2b",
"ctx" : {
  "IP" : "0x188c1a0ac",
  "SP" : "0x2b9a06c40",
  "BP" : "0x2b9a06cd0"
},
"unmanaged_frames" : [
{
  "is_managed" : "false",
  "native_address" : "0x280cffb40",
  "native_offset" : "0x00000"
 }
,
{
  "is_managed" : "false",
  "native_address" : "0x280e35ecc",
  "native_offset" : "0x00000"
 }
,
{
  "is_managed" : "false",
  "native_address" : "0x280e36244",
  "native_offset" : "0x00000"
 }
,
{
  "is_managed" : "false",
  "native_address" : "0x280e35ff0",
  "native_offset" : "0x00000"
 }
,
{
  "is_managed" : "false",
  "native_address" : "0x280d40a30",
  "native_offset" : "0x00000"
 }
,
{
  "is_managed" : "false",
  "native_address" : "0x188c85a24",
  "native_offset" : "0x00000"
 }
,
{
  "is_managed" : "false",
  "native_address" : "0x188c57628",
  "native_offset" : "0x00000"
 }
,
{
  "is_managed" : "false",
  "native_address" : "0x280e854cc",
  "native_offset" : "0x00000"
 }
,
{
  "is_managed" : "false",
  "native_address" : "0x280e8f0ac",
  "native_offset" : "0x00000"
 }
,
{
  "is_managed" : "false",
  "native_address" : "0x280d8df50",
  "native_offset" : "0x00000"
 }
,
{
  "is_managed" : "false",
  "native_address" : "0x280e36cb4",
  "native_offset" : "0x00000"
 }
,
{
  "is_managed" : "false",
  "native_address" : "0x280e36b60",
  "native_offset" : "0x00000"
 }
,
{
  "is_managed" : "false",
  "native_address" : "0x280eb60d0",
  "native_offset" : "0x00000"
 }
,
{
  "is_managed" : "false",
  "native_address" : "0x280eb6058",
  "native_offset" : "0x00000"
 }
,
{
  "is_managed" : "false",
  "native_address" : "0x188c57034",
  "native_offset" : "0x00000"
 }
,
{
  "is_managed" : "false",
  "native_address" : "0x188c51e3c",
  "native_offset" : "0x00000"
 }

]
},
{
"is_managed" : false,
"offset_free_hash" : "0x0",
"offset_rich_hash" : "0x0",
"crashed" : false,
"native_thread_id" : "0x177a1f000",
"thread_info_addr" : "0x2852eca00",
"thread_name" : "tid_d70b",
"ctx" : {
  "IP" : "0x188c16830",
  "SP" : "0x177a1ed20",
  "BP" : "0x177a1ed30"
},
"unmanaged_frames" : [
{
  "is_managed" : "false",
  "native_address" : "0x280cffb40",
  "native_offset" : "0x00000"
 }
,
{
  "is_managed" : "false",
  "native_address" : "0x280e35ecc",
  "native_offset" : "0x00000"
 }
,
{
  "is_managed" : "false",
  "native_address" : "0x280e36244",
  "native_offset" : "0x00000"
 }
,
{
  "is_managed" : "false",
  "native_address" : "0x280e35ff0",
  "native_offset" : "0x00000"
 }
,
{
  "is_managed" : "false",
  "native_address" : "0x280d40a30",
  "native_offset" : "0x00000"
 }
,
{
  "is_managed" : "false",
  "native_address" : "0x188c85a24",
  "native_offset" : "0x00000"
 }
,
{
  "is_managed" : "false",
  "native_address" : "0x188aa9eac",
  "native_offset" : "0x00000"
 }
,
{
  "is_managed" : "false",
  "native_address" : "0x188aaa55c",
  "native_offset" : "0x00000"
 }
,
{
  "is_managed" : "false",
  "native_address" : "0x103a2a2bc",
  "native_offset" : "0x00000"
 }
,
{
  "is_managed" : "false",
  "native_address" : "0x1016950d8",
  "native_offset" : "0x00000"
 }
,
{
  "is_managed" : "false",
  "native_address" : "0x101695d68",
  "native_offset" : "0x00000"
 }
,
{
  "is_managed" : "false",
  "native_address" : "0x1018e201c",
  "native_offset" : "0x00000"
 }
,
{
  "is_managed" : "false",
  "native_address" : "0x188c57034",
  "native_offset" : "0x00000"
 }
,
{
  "is_managed" : "false",
  "native_address" : "0x188c51e3c",
  "native_offset" : "0x00000"
 }

]
},
{
"is_managed" : false,
"offset_free_hash" : "0x0",
"offset_rich_hash" : "0x0",
"crashed" : false,
"native_thread_id" : "0x281733000",
"thread_info_addr" : "0x14690a800",
"thread_name" : "Debugger agent",
"ctx" : {
  "IP" : "0x188c1f200",
  "SP" : "0x281732ad0",
  "BP" : "0x281732af0"
},
"unmanaged_frames" : [
{
  "is_managed" : "false",
  "native_address" : "0x280cffb40",
  "native_offset" : "0x00000"
 }
,
{
  "is_managed" : "false",
  "native_address" : "0x280e35ecc",
  "native_offset" : "0x00000"
 }
,
{
  "is_managed" : "false",
  "native_address" : "0x280e36244",
  "native_offset" : "0x00000"
 }
,
{
  "is_managed" : "false",
  "native_address" : "0x280e35ff0",
  "native_offset" : "0x00000"
 }
,
{
  "is_managed" : "false",
  "native_address" : "0x280d40a30",
  "native_offset" : "0x00000"
 }
,
{
  "is_managed" : "false",
  "native_address" : "0x188c85a24",
  "native_offset" : "0x00000"
 }
,
{
  "is_managed" : "false",
  "native_address" : "0x280d74838",
  "native_offset" : "0x00000"
 }
,
{
  "is_managed" : "false",
  "native_address" : "0x280d6d980",
  "native_offset" : "0x00000"
 }
,
{
  "is_managed" : "false",
  "native_address" : "0x280e36cb4",
  "native_offset" : "0x00000"
 }
,
{
  "is_managed" : "false",
  "native_address" : "0x280e36b60",
  "native_offset" : "0x00000"
 }
,
{
  "is_managed" : "false",
  "native_address" : "0x280eb60d0",
  "native_offset" : "0x00000"
 }
,
{
  "is_managed" : "false",
  "native_address" : "0x280eb6058",
  "native_offset" : "0x00000"
 }
,
{
  "is_managed" : "false",
  "native_address" : "0x188c57034",
  "native_offset" : "0x00000"
 }
,
{
  "is_managed" : "false",
  "native_address" : "0x188c51e3c",
  "native_offset" : "0x00000"
 }

]
},
{
"is_managed" : false,
"offset_free_hash" : "0x0",
"offset_rich_hash" : "0x0",
"crashed" : true,
"native_thread_id" : "0x1dff19300",
"thread_info_addr" : "0x148970a00",
"thread_name" : "tid_103",
"ctx" : {
  "IP" : "0x188891408",
  "SP" : "0x16ee99d90",
  "BP" : "0x16ee99e40"
},
"unmanaged_frames" : [
{
  "is_managed" : "false",
  "native_address" : "0x280cffb40",
  "native_offset" : "0x00000"
 }
,
{
  "is_managed" : "false",
  "native_address" : "0x280e35ecc",
  "native_offset" : "0x00000"
 }
,
{
  "is_managed" : "false",
  "native_address" : "0x280e36244",
  "native_offset" : "0x00000"
 }
,
{
  "is_managed" : "false",
  "native_address" : "0x280e36894",
  "native_offset" : "0x00000"
 }
,
{
  "is_managed" : "false",
  "native_address" : "0x280d4187c",
  "native_offset" : "0x00000"
 }
,
{
  "is_managed" : "false",
  "native_address" : "0x280d03c60",
  "native_offset" : "0x00000"
 }
,
{
  "is_managed" : "false",
  "native_address" : "0x280c8c690",
  "native_offset" : "0x00000"
 }
,
{
  "is_managed" : "false",
  "native_address" : "0x188c85a24",
  "native_offset" : "0x00000"
 }
,
{
  "is_managed" : "false",
  "native_address" : "0x10395b824",
  "native_offset" : "0x00000"
 }
,
{
  "is_managed" : "false",
  "native_address" : "0x189e738e8",
  "native_offset" : "0x00000"
 }
,
{
  "is_managed" : "false",
  "native_address" : "0x188d4fd94",
  "native_offset" : "0x00000"
 }
,
{
  "is_managed" : "false",
  "native_address" : "0x188d4fa3c",
  "native_offset" : "0x00000"
 }
,
{
  "is_managed" : "false",
  "native_address" : "0x188d4f574",
  "native_offset" : "0x00000"
 }
,
{
  "is_managed" : "false",
  "native_address" : "0x188d32a20",
  "native_offset" : "0x00000"
 }
,
{
  "is_managed" : "false",
  "native_address" : "0x188d31c2c",
  "native_offset" : "0x00000"
 }
,
{
  "is_managed" : "false",
  "native_address" : "0x19328a448",
  "native_offset" : "0x00000"
 }
,
{
  "is_managed" : "false",
  "native_address" : "0x19328a0d8",
  "native_offset" : "0x00000"
 }
,
{
  "is_managed" : "false",
  "native_address" : "0x193289fdc",
  "native_offset" : "0x00000"
 }
,
{
  "is_managed" : "false",
  "native_address" : "0x18c50d0ec",
  "native_offset" : "0x00000"
 }
,
{
  "is_managed" : "false",
  "native_address" : "0x18cce0c2c",
  "native_offset" : "0x00000"
 }
,
{
  "is_managed" : "false",
  "native_address" : "0x18c500598",
  "native_offset" : "0x00000"
 }
,
{
  "is_managed" : "false",
  "native_address" : "0x18c4d7864",
  "native_offset" : "0x00000"
 }
,
{
  "is_managed" : "false",
  "native_address" : "0x103975030",
  "native_offset" : "0x00000"
 }
,
{
  "is_managed" : "false",
  "native_address" : "0x1039753a8",
  "native_offset" : "0x00000"
 }
,
{
  "is_managed" : "false",
  "native_address" : "0x1888dd058",
  "native_offset" : "0x00000"
 }

]
}
]
}